terminusdb_client/__init__.py
terminusdb_client/__version__.py
terminusdb_client/errors.py
terminusdb_client/woql_type.py
terminusdb_client/woql_utils.py
terminusdb_client/client/Client.py
terminusdb_client/client/__init__.py
terminusdb_client/query_syntax/__init__.py
terminusdb_client/query_syntax/query_syntax.py
terminusdb_client/schema/__init__.py
terminusdb_client/schema/schema.py
terminusdb_client/scripts/__init__.py
terminusdb_client/scripts/schema_template.py
terminusdb_client/scripts/scripts.py
terminusdb_client/tests/AllServerRecords.py
terminusdb_client/tests/DBRecord.py
terminusdb_client/tests/__init__.py
terminusdb_client/tests/ans_cardinality.py
terminusdb_client/tests/ans_doctype.py
terminusdb_client/tests/ans_insert.py
terminusdb_client/tests/ans_property.py
terminusdb_client/tests/ans_triple_quad.py
terminusdb_client/tests/conftest.py
terminusdb_client/tests/connectCapabilitiesResponse.py
terminusdb_client/tests/connectionObjDump.py
terminusdb_client/tests/getSchemaTurtleResponse.py
terminusdb_client/tests/mockResponse.py
terminusdb_client/tests/serverRecordsFromCap.py
terminusdb_client/tests/test_Client.py
terminusdb_client/tests/test_Schema.py
terminusdb_client/tests/test_backwardsCompat.py
terminusdb_client/tests/test_scripts.py
terminusdb_client/tests/test_woqlCore.py
terminusdb_client/tests/test_woqlExtra.py
terminusdb_client/tests/test_woqlQuery.py
terminusdb_client/tests/integration_tests/__init__.py
terminusdb_client/tests/integration_tests/conftest.py
terminusdb_client/tests/integration_tests/mock_jsons.py
terminusdb_client/tests/integration_tests/test_client.py
terminusdb_client/tests/integration_tests/test_schema.py
terminusdb_client/tests/integration_tests/test_scripts.py
terminusdb_client/tests/woqljson/__init__.py
terminusdb_client/tests/woqljson/woqlAndJson.py
terminusdb_client/tests/woqljson/woqlCastJson.py
terminusdb_client/tests/woqljson/woqlConcatJson.py
terminusdb_client/tests/woqljson/woqlDeleteJson.py
terminusdb_client-10.2.4.dist-info/LICENSE
terminusdb_client-10.2.4.dist-info/METADATA
terminusdb_client-10.2.4.dist-info/WHEEL
terminusdb_client-10.2.4.dist-info/entry_points.txt
terminusdb_client-10.2.4.dist-info/top_level.txt
terminusdb_client-10.2.4.dist-info/RECORD
