Metadata-Version: 2.1
Name: terminusdb-client
Version: 10.2.4
Summary: Python client for Terminus DB
Home-page: https://github.com/terminusdb/terminusdb-client-python
Author: TerminusDB group
Author-email: terminusdatabase@gmail.com
Classifier: Programming Language :: Python :: 3
Classifier: License :: OSI Approved :: Apache Software License
Classifier: Operating System :: OS Independent
Requires-Python: >=3.7
License-File: LICENSE
Requires-Dist: requests
Requires-Dist: numpydoc
Requires-Dist: click (<9.0,>=7.0)
Requires-Dist: shed
Requires-Dist: typeguard (<3,>=2)
Requires-Dist: tqdm
Provides-Extra: dataframe
Requires-Dist: numpy (>=1.13.0) ; extra == 'dataframe'
Requires-Dist: pandas (>=0.23.0) ; extra == 'dataframe'
